ezpp/__init__.py
ezpp/__main__.py
ezpp/frosted.py
ezpp/global_args.py
ezpp/listfonts.py
ezpp/pngs2gif.py
ezpp/recolor.py
ezpp/refmt.py
ezpp/render.py
ezpp/resize.py
ezpp/setup.py
ezpp/shadow.py
ezpp/text2icon.py
ezpp/utils/__init__.py
ezpp/utils/color_parser.py
ezpp/utils/filetype.py
ezpp/utils/fonts.py
ezpp/utils/roundrect.py
ezpp/utils/size_parser.py
ezpp/utils/text.py
ezpp-0.3.3.dist-info/METADATA
ezpp-0.3.3.dist-info/WHEEL
ezpp-0.3.3.dist-info/entry_points.txt
ezpp-0.3.3.dist-info/top_level.txt
ezpp-0.3.3.dist-info/RECORD
